helloWorldAPOKI/__init__.py
helloWorldAPOKI/functions.py
helloWorldAPOKI-1.0.dist-info/METADATA
helloWorldAPOKI-1.0.dist-info/WHEEL
helloWorldAPOKI-1.0.dist-info/top_level.txt
helloWorldAPOKI-1.0.dist-info/RECORD
