Metadata-Version: 2.2
Name: helloWorldAPOKI
Version: 1.0
Summary: Hello World!
Author: apoki0
Author-email: bartosz@winami.com
Classifier: Programming Language :: Python :: 3
Classifier: License :: OSI Approved :: MIT License
Classifier: Operating System :: OS Independent
Requires-Python: >=3.6
Dynamic: author
Dynamic: author-email
Dynamic: classifier
Dynamic: requires-python
Dynamic: summary
